langchain_google_alloydb_pg/__init__.py
langchain_google_alloydb_pg/async_chat_message_history.py
langchain_google_alloydb_pg/async_checkpoint.py
langchain_google_alloydb_pg/async_loader.py
langchain_google_alloydb_pg/async_vectorstore.py
langchain_google_alloydb_pg/chat_message_history.py
langchain_google_alloydb_pg/checkpoint.py
langchain_google_alloydb_pg/embeddings.py
langchain_google_alloydb_pg/engine.py
langchain_google_alloydb_pg/indexes.py
langchain_google_alloydb_pg/loader.py
langchain_google_alloydb_pg/model_manager.py
langchain_google_alloydb_pg/py.typed
langchain_google_alloydb_pg/vectorstore.py
langchain_google_alloydb_pg/version.py
langchain_google_alloydb_pg/utils/pgvector_migrator.py
langchain_google_alloydb_pg-0.12.0.dist-info/licenses/LICENSE
langchain_google_alloydb_pg-0.12.0.dist-info/METADATA
langchain_google_alloydb_pg-0.12.0.dist-info/WHEEL
langchain_google_alloydb_pg-0.12.0.dist-info/top_level.txt
langchain_google_alloydb_pg-0.12.0.dist-info/RECORD
