Metadata-Version: 2.4
Name: langchain-google-alloydb-pg
Version: 0.12.0
Summary: LangChain integrations for Google Cloud AlloyDB for PostgreSQL
Author-email: Google LLC <googleapis-packages@google.com>
License: 
Project-URL: Homepage, https://github.com/googleapis/langchain-google-alloydb-pg-python
Project-URL: Repository, https://github.com/googleapis/langchain-google-alloydb-pg-python.git
Project-URL: Bug Tracker, https://github.com/googleapis/langchain-google-alloydb-pg-python/issues
Project-URL: Changelog, https://github.com/googleapis/langchain-google-alloydb-pg-python/blob/main/CHANGELOG.md
Classifier: Intended Audience :: Developers
Classifier: License :: OSI Approved :: Apache Software License
Classifier: Programming Language :: Python
Classifier: Programming Language :: Python :: 3
Classifier: Programming Language :: Python :: 3.9
Classifier: Programming Language :: Python :: 3.10
Classifier: Programming Language :: Python :: 3.11
Classifier: Programming Language :: Python :: 3.12
Requires-Python: >=3.9
License-File: LICENSE
Requires-Dist: google-cloud-alloydb-connector[asyncpg]<2.0.0,>=1.2.0
Requires-Dist: google-cloud-storage<4.0.0,>=2.18.2
Requires-Dist: langchain-core<1.0.0,>=0.2.36
Requires-Dist: numpy<3.0.0,>=1.24.4; python_version > "3.9"
Requires-Dist: numpy<=2.0.2,>=1.24.4; python_version <= "3.9"
Requires-Dist: pgvector<1.0.0,>=0.2.5
Requires-Dist: SQLAlchemy[asyncio]<3.0.0,>=2.0.25
Provides-Extra: langgraph
Requires-Dist: langgraph-checkpoint<3.0.0,>=2.0.9; extra == "langgraph"
Provides-Extra: test
Requires-Dist: black[jupyter]==25.1.0; extra == "test"
Requires-Dist: isort==6.0.1; extra == "test"
Requires-Dist: langgraph==0.3.31; extra == "test"
Requires-Dist: mypy==1.15.0; extra == "test"
Requires-Dist: pytest-asyncio==0.26.0; extra == "test"
Requires-Dist: pytest==8.3.5; extra == "test"
Requires-Dist: pytest-cov==6.1.1; extra == "test"
Requires-Dist: pytest-depends==1.0.1; extra == "test"
Requires-Dist: Pillow==11.2.1; extra == "test"
Requires-Dist: langchain-tests==0.3.19; extra == "test"
Dynamic: license-file
